yafowil.widget.select2-1.5-py3.9-nspkg.pth
yafowil/widget/select2/__init__.py
yafowil/widget/select2/example.py
yafowil/widget/select2/tests.py
yafowil/widget/select2/widget.py
yafowil/widget/select2/resources/widget.css
yafowil/widget/select2/resources/widget.js
yafowil/widget/select2/resources/select2/LICENSE
yafowil/widget/select2/resources/select2/README.md
yafowil/widget/select2/resources/select2/component.json
yafowil/widget/select2/resources/select2/release.sh
yafowil/widget/select2/resources/select2/select2-bootstrap.css
yafowil/widget/select2/resources/select2/select2-spinner.gif
yafowil/widget/select2/resources/select2/select2.css
yafowil/widget/select2/resources/select2/select2.jquery.json
yafowil/widget/select2/resources/select2/select2.js
yafowil/widget/select2/resources/select2/select2.min.js
yafowil/widget/select2/resources/select2/select2.png
yafowil/widget/select2/resources/select2/select2_locale_ar.js
yafowil/widget/select2/resources/select2/select2_locale_az.js
yafowil/widget/select2/resources/select2/select2_locale_bg.js
yafowil/widget/select2/resources/select2/select2_locale_ca.js
yafowil/widget/select2/resources/select2/select2_locale_cs.js
yafowil/widget/select2/resources/select2/select2_locale_da.js
yafowil/widget/select2/resources/select2/select2_locale_de.js
yafowil/widget/select2/resources/select2/select2_locale_el.js
yafowil/widget/select2/resources/select2/select2_locale_en.js.template
yafowil/widget/select2/resources/select2/select2_locale_es.js
yafowil/widget/select2/resources/select2/select2_locale_et.js
yafowil/widget/select2/resources/select2/select2_locale_eu.js
yafowil/widget/select2/resources/select2/select2_locale_fa.js
yafowil/widget/select2/resources/select2/select2_locale_fi.js
yafowil/widget/select2/resources/select2/select2_locale_fr.js
yafowil/widget/select2/resources/select2/select2_locale_gl.js
yafowil/widget/select2/resources/select2/select2_locale_he.js
yafowil/widget/select2/resources/select2/select2_locale_hr.js
yafowil_widget_select2-1.5.dist-info/licenses/LICENSE.rst
yafowil_widget_select2-1.5.dist-info/METADATA
yafowil_widget_select2-1.5.dist-info/WHEEL
yafowil_widget_select2-1.5.dist-info/entry_points.txt
yafowil_widget_select2-1.5.dist-info/namespace_packages.txt
yafowil_widget_select2-1.5.dist-info/top_level.txt
yafowil_widget_select2-1.5.dist-info/RECORD
